{
  "films": [
    {
      "0": { "name": "Agassi", "real": "Chan-Wook Park", "duree": "02:25" },
      "1": { "name": "The BFG", "real": "Steven Spielberg", "duree": "01:55" },
      "2": { "name": "Mal de pierres", "real": "Nicole Garcia", "duree": "02:00" },
      "3": { "name": "American Honey", "real": "Andrea Arnold", "duree": "02:42" },
      "4": { "name": "", "real": "", "duree": "" },
      "5": { "name": "", "real": "", "duree": "" },
      "6": { "name": "", "real": "", "duree": "" },
      "7": { "name": "", "real": "", "duree": "" },
      "8": { "name": "", "real": "", "duree": "" },
      "9": { "name": "", "real": "", "duree": "" },
      "10": { "name": "", "real": "", "duree": "" },
      "11": { "name": "", "real": "", "duree": "" },
      "12": { "name": "", "real": "", "duree": "" },
      "13": { "name": "", "real": "", "duree": "" },
      "14": { "name": "", "real": "", "duree": "" },
      "15": { "name": "", "real": "", "duree": "" },
      "16": { "name": "", "real": "", "duree": "" },
      "17": { "name": "", "real": "", "duree": "" },
      "18": { "name": "", "real": "", "duree": "" },
    }
  ]
}